{
    "data": [
        {
            "bizCate": "-1",
            "level": "1",
            "sortIndex": "1",
            "promptDetail": null,
            "nodeType": "1",
            "parentId": "16593",
            "ename": null,
            "offlineDate": null,
            "extraProp": {
                "value": "ALL",
                "channelId": "ALL"
            },
            "scope": "101",
            "bizId": null,
            "name": "所有销售渠道",
            "id": "16596",
            "aid": "16596",
            "promptTip": null,
            "status": null
        },
        {
            "bizCate": "-1",
            "level": "1",
            "sortIndex": "2",
            "promptDetail": null,
            "nodeType": "1",
            "parentId": "16593",
            "ename": "",
            "offlineDate": null,
            "extraProp": {
                "value": "1",
                "channelId": "1"
            },
            "scope": "101",
            "bizId": "1",
            "name": "天猫国际",
            "id": "16600",
            "aid": "16600",
            "promptTip": null,
            "status": null
        },
        {
            "bizCate": "-1",
            "level": "1",
            "sortIndex": "3",
            "promptDetail": null,
            "nodeType": "1",
            "parentId": "16593",
            "ename": null,
            "offlineDate": null,
            "extraProp": {
                "value": "13",
                "channelId": "13"
            },
            "scope": "101",
            "bizId": "13",
            "name": "天猫国际直营",
            "id": "16604",
            "aid": "16604",
            "promptTip": null,
            "status": null
        },
        {
            "bizCate": "-1",
            "level": "1",
            "sortIndex": "5",
            "promptDetail": null,
            "nodeType": "1",
            "parentId": "16593",
            "ename": "",
            "offlineDate": null,
            "extraProp": {
                "value": "4",
                "channelId": "4"
            },
            "scope": "101",
            "bizId": "4",
            "name": "天猫",
            "id": "16612",
            "aid": "16612",
            "promptTip": null,
            "status": null
        },
        {
            "bizCate": "-1",
            "level": "1",
            "sortIndex": "6",
            "promptDetail": null,
            "nodeType": "1",
            "parentId": "16593",
            "ename": "",
            "offlineDate": null,
            "extraProp": {
                "value": "5",
                "channelId": "995"
            },
            "scope": "101",
            "bizId": "995",
            "name": "全球购",
            "id": "16616",
            "aid": "16616",
            "promptTip": null,
            "status": null
        },
        {
            "bizCate": "-1",
            "level": "1",
            "sortIndex": "7",
            "promptDetail": null,
            "nodeType": "1",
            "parentId": "16593",
            "ename": "",
            "offlineDate": null,
            "extraProp": {
                "value": "3",
                "channelId": "3"
            },
            "scope": "101",
            "bizId": "3",
            "name": "淘宝集市",
            "id": "16620",
            "aid": "16620",
            "promptTip": null,
            "status": null
        }
    ],
    "errCode": 0,
    "errMsg": "Success",
    "codeClass": "SUCCESS"
}